[{"Id":"97948278-039c-423e-ab9f-81aacaca7529","Status":1,"OrderDate":"2022-05-03T18:20:04.4047723+03:00","Cart":{"CartLines":[{"Product":{"Id":2,"Name":"Hamburger","Cost":120.0,"Description":"бургер с говяжьей котлетой"},"Amount":1,"Cost":120.0}],"Id":7,"UserId":"UserId","CartCost":120.0,"Amount":1.0},"UserId":"UserId","OrderData":{"Cart":null,"Name":"1","Adress":"1","Email":"1"}},{"Id":"47a507b5-0649-4972-a1e9-f806bb943609","Status":2,"OrderDate":"2022-05-03T18:28:00.2881798+03:00","Cart":{"CartLines":[{"Product":{"Id":3,"Name":"Bigburger","Cost":200.0,"Description":"бургер с двойной говяжьей котлетой"},"Amount":3,"Cost":600.0}],"Id":8,"UserId":"UserId","CartCost":600.0,"Amount":3.0},"UserId":"UserId","OrderData":{"Cart":null,"Name":"2","Adress":"2","Email":"2"}},{"Id":"ad8da451-e477-4978-b43a-a9e08e670555","Status":4,"OrderDate":"2022-05-03T18:31:07.8800451+03:00","Cart":{"CartLines":[{"Product":{"Id":3,"Name":"Bigburger","Cost":200.0,"Description":"бургер с двойной говяжьей котлетой"},"Amount":4,"Cost":800.0}],"Id":9,"UserId":"UserId","CartCost":800.0,"Amount":4.0},"UserId":"UserId","OrderData":{"Cart":null,"Name":"3","Adress":"3","Email":"3"}}]
